tagasuri/__init__.py
tagasuri/__main__.py
tagasuri/app.py
tagasuri/epd.py
tagasuri/logging.py
tagasuri-0.5.0.dist-info/LICENSE
tagasuri-0.5.0.dist-info/METADATA
tagasuri-0.5.0.dist-info/WHEEL
tagasuri-0.5.0.dist-info/entry_points.txt
tagasuri-0.5.0.dist-info/top_level.txt
tagasuri-0.5.0.dist-info/RECORD
