Metadata-Version: 2.1
Name: tagasuri
Version: 0.5.0
Summary: Test engine on different test sets.
Home-page: https://github.com/fsmosca/tagasuri
Author: Ferdinand Mosca
Author-email: ferdymosca@gmail.com
Project-URL: Bug Tracker, https://github.com/fsmosca/tagasuri/issues
Classifier: Programming Language :: Python :: 3
Classifier: License :: OSI Approved :: GNU General Public License v3 (GPLv3)
Classifier: Operating System :: OS Independent
Classifier: Development Status :: 4 - Beta
Classifier: Intended Audience :: Developers
Classifier: Intended Audience :: End Users/Desktop
Classifier: Intended Audience :: Science/Research
Requires-Python: >=3.7
License-File: LICENSE
Requires-Dist: chess
Requires-Dist: pretty-html-table
Requires-Dist: pandas
